ViewLogger/Common.py
ViewLogger/__init__.py
ViewLogger/admin.py
ViewLogger/api.py
ViewLogger/apps.py
ViewLogger/forms.py
ViewLogger/middleware.py
ViewLogger/models.py
ViewLogger/tables.py
ViewLogger/tests.py
ViewLogger/urls.py
ViewLogger/views.py
ViewLogger/management/__init__.py
ViewLogger/management/commands/ArchiveViewLoggerTable.py
ViewLogger/management/commands/LoadViewLoggerTable.py
ViewLogger/management/commands/SearchInViewLoggerArchives.py
ViewLogger/management/commands/__init__.py
ViewLogger/migrations/0001_initial.py
ViewLogger/migrations/0002_log_duration.py
ViewLogger/migrations/__init__.py
ViewLogger/templates/mainLog.html
ViewLogger/templates/searchInViewLogger.html
ViewLogger-2.2.2.dist-info/LICENSE
ViewLogger-2.2.2.dist-info/METADATA
ViewLogger-2.2.2.dist-info/WHEEL
ViewLogger-2.2.2.dist-info/top_level.txt
ViewLogger-2.2.2.dist-info/RECORD
